emdash_ai/__init__.py
emdash_ai-0.1.107.dist-info/METADATA
emdash_ai-0.1.107.dist-info/WHEEL
emdash_ai-0.1.107.dist-info/entry_points.txt
emdash_ai-0.1.107.dist-info/RECORD
