Metadata-Version: 2.4
Name: emdash-ai
Version: 0.1.107
Summary: Graph-based coding intelligence system - The 'Senior Engineer' Context Engine
Author: Em Dash Team
Requires-Python: >=3.10
Requires-Dist: astroid>=3.0.1
Requires-Dist: click>=8.1.7
Requires-Dist: cmake>=3.25.0
Requires-Dist: emdash-cli
Requires-Dist: emdash-core
Requires-Dist: gitpython>=3.1.40
Requires-Dist: httpx>=0.25.0
Requires-Dist: kuzu>=0.4.0
Requires-Dist: loguru>=0.7.2
Requires-Dist: networkx>=3.2.1
Requires-Dist: numpy>=1.26.0
Requires-Dist: openai>=1.0.0
Requires-Dist: prompt-toolkit>=3.0.43
Requires-Dist: pydantic>=2.5.0
Requires-Dist: pygithub>=2.1.1
Requires-Dist: pypng>=0.0.21
Requires-Dist: python-dotenv>=1.0.0
Requires-Dist: python-louvain>=0.16
Requires-Dist: rich>=13.7.0
Requires-Dist: scipy>=1.11.4
Requires-Dist: supabase>=2.0.0
Requires-Dist: textual>=0.47.0
Requires-Dist: tqdm>=4.66.1
Provides-Extra: dev
Requires-Dist: black>=23.11.0; extra == 'dev'
Requires-Dist: mypy>=1.7.1; extra == 'dev'
Requires-Dist: pyinstaller<7.0,>=6.0; extra == 'dev'
Requires-Dist: pytest-cov>=4.1.0; extra == 'dev'
Requires-Dist: pytest>=7.4.3; extra == 'dev'
Requires-Dist: ruff>=0.1.6; extra == 'dev'
Provides-Extra: local
Requires-Dist: accelerate>=0.25.0; extra == 'local'
Requires-Dist: torch>=2.1.0; extra == 'local'
Requires-Dist: transformers>=4.36.0; extra == 'local'
